neuralnetlogical/__init__.py
neuralnetlogical/scripts/__init__.py
neuralnetlogical/scripts/andGate.py
neuralnetlogical/scripts/nandGate.py
neuralnetlogical/scripts/norGate.py
neuralnetlogical/scripts/notGate.py
neuralnetlogical/scripts/orGate.py
neuralnetlogical-0.0.0.dist-info/METADATA
neuralnetlogical-0.0.0.dist-info/WHEEL
neuralnetlogical-0.0.0.dist-info/top_level.txt
neuralnetlogical-0.0.0.dist-info/RECORD
